avalancheetl
blockchainetl
