Metadata-Version: 2.1
Name: avalanche-etl
Version: 0.0.2
Summary: Tools for exporting Avalanche blockchain data to CSV or JSON
Home-page: https://github.com/shaikhzhas/avalanche-etl
Author: Zhassulan Shaikhygali
Author-email: shaikh.zhas@gmail.com
License: UNKNOWN
Project-URL: Bug Reports, https://github.com/shaikhzhas/avalanche-etl/issues
Project-URL: Source, https://github.com/shaikhzhas/avalanche-etl
Keywords: avalanche,blockchain,etl
Platform: UNKNOWN
Classifier: Development Status :: 5 - Production/Stable
Classifier: Intended Audience :: Developers
Classifier: License :: OSI Approved :: MIT License
Classifier: Programming Language :: Python :: 3
Classifier: Programming Language :: Python :: 3.7
Classifier: Programming Language :: Python :: 3.8
Classifier: Programming Language :: Python :: 3.9
Requires-Python: >=3.7.2,<4
Provides-Extra: streaming
Provides-Extra: streaming-kinesis
Provides-Extra: dev
